c7n_openstack/__init__.py
c7n_openstack/client.py
c7n_openstack/entry.py
c7n_openstack/filters.py
c7n_openstack/provider.py
c7n_openstack/query.py
c7n_openstack/resources/__init__.py
c7n_openstack/resources/flavor.py
c7n_openstack/resources/object_storage.py
c7n_openstack/resources/project.py
c7n_openstack/resources/resource_map.py
c7n_openstack/resources/secret.py
c7n_openstack/resources/security_group.py
c7n_openstack/resources/server.py
c7n_openstack/resources/user.py
c7n_openstack/resources/volume.py
c7n_openstack-0.1.39.dist-info/METADATA
c7n_openstack-0.1.39.dist-info/WHEEL
c7n_openstack-0.1.39.dist-info/RECORD
